ocient_graph/__init__.py
ocient_graph-1.0.0.dist-info/WHEEL
ocient_graph-1.0.0.dist-info/METADATA
ocient_graph-1.0.0.dist-info/RECORD
