Metadata-Version: 2.1
Name: ocient_graph
Author: Ocient Inc
Author-email: info@ocient.com
Home-page: https://www.ocient.com/
License: Apache License, Version 2.0
Summary: Ocient Graph Utilities built on top of pyocient
Requires-Python: >=3.7,<4
Requires-Dist: pyocient
Version: 1.0.0
